simcrf/__init__.py
simcrf/features.py
simcrf/model.py
simcrf/utils.py
simcrf-0.1.8.dist-info/METADATA
simcrf-0.1.8.dist-info/RECORD
simcrf-0.1.8.dist-info/WHEEL
simcrf-0.1.8.dist-info/top_level.txt
