Metadata-Version: 2.1
Name: simcrf
Version: 0.1.8
Summary: simple and quick crf wrapper for crfsuite
Home-page: https://github.com/eromoe/SimCRF
Author: Mithril | eromoe
Author-email: eromoe@users.noreply.github.com
License: UNKNOWN
Keywords: c,r,f, ,c,r,f,s,u,i,t,e
Platform: UNKNOWN
Classifier: Development Status :: 4 - Beta
Classifier: Programming Language :: Python :: 2
Classifier: Programming Language :: Python :: 2.6
Classifier: Programming Language :: Python :: 2.7
Classifier: Programming Language :: Python :: 3
Classifier: Programming Language :: Python :: 3.3
Classifier: Programming Language :: Python :: 3.4
Classifier: Intended Audience :: Developers
Classifier: Operating System :: OS Independent
Classifier: Environment :: Web Environment
Classifier: License :: OSI Approved :: MIT License
Classifier: Topic :: Scientific/Engineering :: Information Analysis
Classifier: Topic :: Software Development :: Libraries :: Python Modules
Requires-Dist: sklearn-crfsuite
Requires-Dist: numpy
Requires-Dist: jieba
Requires-Dist: six
Requires-Dist: pytest
